{"trial_id": "0", "hyperparameters": {"space": [{"class_name": "Int", "config": {"name": "units", "default": null, "conditions": [], "min_value": 30, "max_value": 300, "step": 30, "sampling": "linear"}}, {"class_name": "Int", "config": {"name": "num_of_SimpleRNN_layers", "default": null, "conditions": [], "min_value": 0, "max_value": 5, "step": 1, "sampling": "linear"}}, {"class_name": "Int", "config": {"name": "units_final", "default": null, "conditions": [], "min_value": 30, "max_value": 300, "step": 30, "sampling": "linear"}}, {"class_name": "Choice", "config": {"name": "learning_rate", "default": 0.01, "conditions": [], "values": [0.01, 0.001, 0.0001], "ordered": true}}], "values": {"units": 180, "num_of_SimpleRNN_layers": 0, "units_final": 150, "learning_rate": 0.001}}, "metrics": {"metrics": {"loss": {"direction": "min", "observations": [{"value": [0.022918932139873505], "step": 2}]}, "val_loss": {"direction": "min", "observations": [{"value": [0.003468967042863369], "step": 2}]}}}, "score": 0.003468967042863369, "best_step": 2, "status": "COMPLETED", "message": null}